{"status":true,"updated_at_utc":"2026-07-16 18:42:08","server_time":1784227328,"odds":{"1554447":{"home_team_id":4358,"away_team_id":568,"updated":40,"status":"First Half","match_winner":{"home":"41","draw":"8","away":"1.083"},"next_goal":{"home":null,"none":null,"away":null}},"1554449":{"home_team_id":651,"away_team_id":702,"updated":26,"status":"First Half","match_winner":{"home":"1.909","draw":"1.952","away":"13"},"next_goal":{"home":null,"none":null,"away":null}},"1554452":{"home_team_id":3554,"away_team_id":608,"updated":13,"status":"First Half","match_winner":{"home":"3.4","draw":"1.909","away":"3.4"},"next_goal":{"home":null,"none":null,"away":null}},"1494706":{"home_team_id":326,"away_team_id":757,"updated":81,"status":"Second Half","match_winner":null,"next_goal":null},"1554416":{"home_team_id":388,"away_team_id":20406,"updated":86,"status":"Second Half","match_winner":null,"next_goal":{"home":null,"none":null,"away":null}},"1554420":{"home_team_id":591,"away_team_id":2191,"updated":82,"status":"Second Half","match_winner":null,"next_goal":null},"1554429":{"home_team_id":691,"away_team_id":3381,"updated":84,"status":"Second Half","match_winner":null,"next_goal":null}}}