{"status":true,"updated_at_utc":"2026-07-15 18:38:06","server_time":1784140686,"odds":{"1554375":{"home_team_id":15847,"away_team_id":701,"updated":22,"status":"First Half","match_winner":{"home":"11","draw":"4","away":"1.285"},"next_goal":{"home":null,"none":null,"away":null}},"1554421":{"home_team_id":3745,"away_team_id":661,"updated":7,"status":"First Half","match_winner":{"home":"3.4","draw":"1.952","away":"3.4"},"next_goal":{"home":null,"none":null,"away":null}},"1583327":{"home_team_id":200,"away_team_id":575,"updated":71,"status":"Second Half","match_winner":null,"next_goal":{"home":null,"none":null,"away":null}}}}